{
  "mission_id": "MIS-20260518-004",
  "generated_at": "2026-05-18T20:44:59.202606+00:00",
  "files": [
    {
      "path": "01_mission_brief.md",
      "size_bytes": 214,
      "ext": ".md"
    },
    {
      "path": "02_context_used.md",
      "size_bytes": 220,
      "ext": ".md"
    },
    {
      "path": "03_execution_plan.md",
      "size_bytes": 387,
      "ext": ".md"
    },
    {
      "path": "04_squad_assigned.md",
      "size_bytes": 142,
      "ext": ".md"
    },
    {
      "path": "mission_contract.json",
      "size_bytes": 348,
      "ext": ".json"
    },
    {
      "path": "relatorio_final.md",
      "size_bytes": 1126,
      "ext": ".md"
    },
    {
      "path": "05_outputs/10_hooks.md",
      "size_bytes": 3007,
      "ext": ".md"
    },
    {
      "path": "05_outputs/10_roteiros.md",
      "size_bytes": 14989,
      "ext": ".md"
    },
    {
      "path": "05_outputs/briefing_edicao.md",
      "size_bytes": 12253,
      "ext": ".md"
    },
    {
      "path": "05_outputs/capas.md",
      "size_bytes": 7787,
      "ext": ".md"
    },
    {
      "path": "05_outputs/legendas.md",
      "size_bytes": 11292,
      "ext": ".md"
    },
    {
      "path": "05_outputs/textos_de_tela.md",
      "size_bytes": 7636,
      "ext": ".md"
    },
    {
      "path": "06_exports/package_manifest.json",
      "size_bytes": 192,
      "ext": ".json"
    }
  ],
  "total_files": 13,
  "total_bytes": 59593
}